cloudgenerator/__init__.py
cloudgenerator/cloudgenerator.py
cloudgenerator-0.1.0.dist-info/METADATA
cloudgenerator-0.1.0.dist-info/WHEEL
cloudgenerator-0.1.0.dist-info/top_level.txt
cloudgenerator-0.1.0.dist-info/RECORD
