Metadata-Version: 2.1
Name: cloudgenerator
Version: 0.1.0
Summary: A safe genetator write cloudgenerator.help() to see commands
Author: NoticedCloud
Author-email: noticedcloud@gmail.com
Keywords: python,password,token,safe
Classifier: Development Status :: 1 - Planning
Classifier: Intended Audience :: Developers
Classifier: Programming Language :: Python :: 3
Classifier: Operating System :: Unix
Classifier: Operating System :: MacOS :: MacOS X
Classifier: Operating System :: Microsoft :: Windows
Requires-Dist: pycryptodome
Requires-Dist: cryptography
